fima/IFB.py
fima/IME.py
fima/Options.py
fima/__init__.py
fima-0.3.1.dist-info/licenses/LICENSE
fima-0.3.1.dist-info/METADATA
fima-0.3.1.dist-info/WHEEL
fima-0.3.1.dist-info/top_level.txt
fima-0.3.1.dist-info/RECORD
