Metadata-Version: 2.4
Name: fima
Version: 0.3.1
Summary: fima – A Python package for scraping and analyzing Iran’s financial market data.
Author-email: Hemo Boghosian <HemoBoghosian@gmail.com>
License-Expression: MIT
Project-URL: Homepage, https://github.com/hemoboghosian/fima
Classifier: Programming Language :: Python :: 3
Classifier: Operating System :: OS Independent
Classifier: Development Status :: 3 - Alpha
Classifier: Intended Audience :: Developers
Classifier: Topic :: Office/Business :: Financial :: Investment
Requires-Python: >=3.10
License-File: LICENSE
Requires-Dist: pandas
Requires-Dist: requests
Requires-Dist: jdatetime
Requires-Dist: numpy
Requires-Dist: scipy
Requires-Dist: bs4
Requires-Dist: selenium
Requires-Dist: mibian
Requires-Dist: lxml
Dynamic: license-file
